absynthe/__init__.py
absynthe/behavior.py
absynthe/graph_builder.py
absynthe/version.py
absynthe/cfg/__init__.py
absynthe/cfg/graph.py
absynthe/cfg/logger_node.py
absynthe/cfg/node.py
absynthe/cfg/utils.py
test/__init__.py
test/test_behavior.py
test/test_graph_builder.py
test/cfg/__init__.py
test/cfg/test_BinomialNode.py
test/cfg/test_Graph.py
test/cfg/test_Node.py
test/cfg/test_UniformNode.py
test/cfg/test_logger_node.py
absynthe-0.0.3.dist-info/LICENSE
absynthe-0.0.3.dist-info/METADATA
absynthe-0.0.3.dist-info/WHEEL
absynthe-0.0.3.dist-info/top_level.txt
absynthe-0.0.3.dist-info/RECORD
