Metadata-Version: 2.1
Name: absynthe
Version: 0.0.3
Summary: A (branching) Behaviour Synthesizer
Home-page: https://github.com/chaturv3di/absynthe/
Author: Namit Chaturvedi
License: Apache License 2.0
Platform: UNKNOWN
Classifier: Development Status :: 3 - Alpha
Classifier: License :: OSI Approved :: Apache Software License
Classifier: Programming Language :: Python :: 3.7
Classifier: Programming Language :: Python :: 3.6
Classifier: Topic :: Internet :: Log Analysis
Classifier: Topic :: Software Development :: Libraries :: Python Modules
Requires-Python: >=3.6.0
Requires-Dist: scipy (==1.2.1)
Requires-Dist: numpy (==1.16.4)
